hmmBaumWelch/__init__.py
hmmBaumWelch/BaumWelch.py
hmmbaumwelch-0.0.1.dist-info/LICENSE
hmmbaumwelch-0.0.1.dist-info/METADATA
hmmbaumwelch-0.0.1.dist-info/WHEEL
hmmbaumwelch-0.0.1.dist-info/RECORD
