Metadata-Version: 2.1
Name: hmmBaumWelch
Version: 0.0.1
Summary: Expectation maximisation and inference for hidden Markov models with one or multiple variables.
Home-page: https://github.com/george-stanley/hmmBaumWelch
Author: George Stanley
Author-email: georgejjstanley@gmail.com
Maintainer: George Stanley
Maintainer-email: georgejjstanley@gmail.com
Requires-Python: >=3.9,<4.0
Classifier: Programming Language :: Python :: 3
Classifier: Programming Language :: Python :: 3.9
Classifier: Programming Language :: Python :: 3.10
Classifier: Programming Language :: Python :: 3.11
Requires-Dist: numpy (>=1.18.0,<=1.26.0)
Requires-Dist: scipy (>=1.6.0)
